jonq/__init__.py
jonq/api.py
jonq/ast.py
jonq/csv_utils.py
jonq/error_handler.py
jonq/executor.py
jonq/generator.py
jonq/jq_filter.py
jonq/jq_worker_cli.py
jonq/json_utils.py
jonq/main.py
jonq/parser.py
jonq/query_parser.py
jonq/stream_utils.py
jonq/tokenizer.py
jonq-0.1.0.dist-info/METADATA
jonq-0.1.0.dist-info/WHEEL
jonq-0.1.0.dist-info/entry_points.txt
jonq-0.1.0.dist-info/RECORD
