Metadata-Version: 2.4
Name: jonq
Version: 0.1.0
Summary: SQL-like query tool for JSON files
Project-URL: Homepage, https://github.com/duriantaco/jonq
Project-URL: Bug Tracker, https://github.com/duriantaco/jonq/issues
Author-email: oha <aaronoh2015@gmail.com>
License: MIT
Keywords: jq,json,query,sql
Classifier: Development Status :: 3 - Alpha
Classifier: Intended Audience :: Developers
Classifier: License :: OSI Approved :: MIT License
Classifier: Programming Language :: Python :: 3
Classifier: Programming Language :: Python :: 3.9
Classifier: Programming Language :: Python :: 3.10
Classifier: Programming Language :: Python :: 3.11
Requires-Python: >=3.9
Requires-Dist: aiofiles
Requires-Dist: orjson>=3.8.0
Provides-Extra: docs
Requires-Dist: myst-parser; extra == 'docs'
Requires-Dist: sphinx; extra == 'docs'
Requires-Dist: sphinx-autodoc-typehints; extra == 'docs'
Requires-Dist: sphinx-rtd-theme; extra == 'docs'
